{
  "config": {
    "title": "Tim DDR",
    "description": "The Official Web Residence Of Tim DDR",
    "theme": "orange",
    "font": "modern",
    "copyright": "© 2025 Tim DDR"
  },
  "artist": {
    "name": "Tim DDR",
    "description": "Indie musician and songwriter",
    "bio": "Creating sounds, mixing words, voicing beats",
    "picture": "/img/profile.jpg"
  },
  "socials": {
    "instagram": "https://www.youtube.com/@violent-cucumber",
    "facebook": "https://www.youtube.com/@violent-cucumber",
    "x": "https://www.youtube.com/@violent-cucumber",
    "youtube": "https://www.youtube.com/@violent-cucumber",
    "tiktok": "https://www.youtube.com/@violent-cucumber"
  },
  "booking": {
    "email": "tima.loenko@gmail.com",
    "phone": "+7 961 214 16 74"
  },
  "shows": [
    {
      "title": "Live In North Palmira",
      "date": "2025-11-14",
      "city": "St.Petersburg",
      "country": "Russia",
      "venue": "Nevsky",
      "tickets": "https://ddr.rocks",
      "available": true
    },
    {
      "title": "Run Away",
      "date": "2025-12-08",
      "city": "Abu Dhabi",
      "country": "UAE",
      "venue": "Corniche",
      "tickets": "https://ddr.rocks",
      "available": true
    }
  ],
  "releases": [
    {
      "title": "Live On Embarkment",
      "album": "Live Set Of Irbitsky Trakt",
      "releaseDate": "2025-10-25",
      "cover": "/img/covers/it.jpg",
      "links": {
        "spotify": "https://vk.com/club232259892",
        "applemusic": "https://vk.com/club232259892",
        "youtube": "https://vk.com/club232259892"
      }
    },
    {
      "title": "Work Of A Dream",
      "album": "New Electric Album",
      "releaseDate": "2025-11-02",
      "cover": "/img/covers/cover1.webp",
      "links": {
        "spotify": "https://ddr.rocks",
        "applemusic": "https://ddr.rocks",
        "youtube": "https://ddr.rocks"
      }
    }
  ],
  "links": [
    {
      "label": "Irbitsky Trakt",
      "description": "The young pop-rock band where Tim sings and rules the keys",
      "url": "https://t.me/@irbittract",
      "icon": "website"
    },
    {
      "label": "Elf&Petroff",
      "description": "The heavy-metal family band project",
      "url": "https://elfandpetroff.com",
      "icon": "website"
    }
  ]
}
